plivo_stream/__init__.py
plivo_stream/base.py
plivo_stream/types.py
plivo_stream/fastapi/__init__.py
plivo_stream/fastapi/streaming.py
plivo_stream/websockets/__init__.py
plivo_stream/websockets/streaming.py
plivo_stream_sdk-0.1.1.dist-info/licenses/LICENSE
plivo_stream_sdk-0.1.1.dist-info/METADATA
plivo_stream_sdk-0.1.1.dist-info/WHEEL
plivo_stream_sdk-0.1.1.dist-info/top_level.txt
plivo_stream_sdk-0.1.1.dist-info/RECORD
