Metadata-Version: 2.4
Name: plivo-stream-sdk
Version: 0.1.1
Summary: Official Python SDK for the Plivo Streaming API with asyncio, WebSockets and FastAPI support
Author-email: Plivo <sdks@plivo.com>
License-Expression: MIT
Project-URL: Repository, https://github.com/plivo/plivo-stream-sdk-python
Project-URL: Issues, https://github.com/plivo/plivo-stream-sdk-python/issues
Classifier: Intended Audience :: Developers
Classifier: Programming Language :: Python :: 3
Classifier: Programming Language :: Python :: 3.9
Classifier: Programming Language :: Python :: 3.10
Classifier: Programming Language :: Python :: 3.11
Classifier: Programming Language :: Python :: 3.12
Classifier: Framework :: FastAPI
Classifier: Topic :: Software Development :: Libraries :: Python Modules
Requires-Python: >=3.9
License-File: LICENSE
Requires-Dist: fastapi>=0.104.0
Requires-Dist: websockets>=12.0
Requires-Dist: pydantic>=2.0.0
Provides-Extra: dev
Requires-Dist: uvicorn[standard]>=0.24.0; extra == "dev"
Requires-Dist: deepgram-sdk>=5.3.0; extra == "dev"
Requires-Dist: plivo>=4.59.3; extra == "dev"
Requires-Dist: elevenlabs>=2.22.0; extra == "dev"
Requires-Dist: openai>=2.6.1; extra == "dev"
Dynamic: license-file
